{
  "3dobj.200": { "Palette": "pal.22", "Width": 57 },
  "3dobj.201": { "Palette": "pal.22", "Width": 48 },
  "3dobj.202": { "Palette": "pal.22", "Width": 32 },
  "3dobj.203": { "Palette": "pal.22", "Width": 18 },
  "3dobj.204": { "Palette": "pal.22", "Width": 21 },
  "3dobj.205": { "Palette": "pal.22", "Width": 67 },
  "3dobj.206": { "Palette": "pal.22", "Width": 68 },
  "3dobj.207": { "Palette": "pal.22", "Width": 50, "ExtraBytes": 21 },
  "3dobj.208": { "Palette": "pal.22", "Width": 28 },
  "3dobj.209": { "Palette": "pal.22", "Width": 25 },
  "3dobj.210": { "Palette": "pal.22", "Width": 21, "ExtraBytes": 11 },
  "3dobj.211": { "Palette": "pal.22", "Width": 15 },
  "3dobj.212": { "Palette": "pal.15", "Width": 106 },
  "3dobj.213": { "Palette": "pal.15", "Width": 140 },
  "3dobj.214": { "Palette": "pal.15", "Width": 100 },
  "3dobj.215": { "Palette": "pal.15", "Width": 96 },
  "3dobj.216": { "Palette": "pal.15", "Width": 56 },
  "3dobj.217": { "Palette": "pal.15", "Width": 63 },
  "3dobj.218": { "Palette": "pal.15", "Width": 63 },
  "3dobj.219": { "Palette": "pal.15", "Width": 63 },
  "3dobj.220": { "Palette": "pal.15", "Width": 65 },
  "3dobj.221": { "Palette": "pal.15", "Width": 122 },
  "3dobj.222": { "Palette": "pal.15", "Width": 38 },
  "3dobj.223": { "Palette": "pal.15", "Width": 57 },
  "3dobj.224": { "Palette": "pal.15", "Width": 33, "ExtraBytes": 24 },
  "3dobj.225": { "Palette": "pal.15", "Width": 42 },
  "3dobj.226": { "Palette": "pal.15", "Width": 30 },
  "3dobj.227": { "Palette": "pal.15", "Width": 17 },
  "3dobj.228": { "Palette": "pal.15", "Width": 12 },
  "3dobj.229": { "Palette": "pal.15", "Width": 16 },
  "3dobj.230": { "Palette": "pal.15", "Width": 8 },
  "3dobj.231": { "Palette": "pal.15", "Width": 7 },
  "3dobj.232": { "Palette": "pal.15", "Width": 68 },
  "3dobj.233": { "Palette": "pal.15", "Width": 71 },
  "3dobj.234": { "Palette": "pal.15", "Width": 85 },
  "3dobj.235": { "Palette": "pal.3", "Width": 51, "Height": 130 },
  "3dobj.236": { "Palette": "pal.3", "Width": 51, "Height": 129 },
  "3dobj.237": { "Palette": "pal.3", "Width": 50, "Height": 128 },
  "3dobj.238": { "Palette": "pal.3", "Width": 50, "Height": 129 },
  "3dobj.239": { "Palette": "pal.3", "Width": 56, "Height": 56 },
  "3dobj.240": { "Palette": "pal.3", "Width": 27, "Height": 74 },
  "3dobj.241": { "Palette": "pal.3", "Width": 55 },
  "3dobj.242": { "Palette": "pal.3", "Width": 55 },
  "3dobj.243": { "Palette": "pal.3", "Width": 55 },
  "3dobj.244": { "Palette": "pal.3", "Width": 100, "Height": 100 },
  "3dobj.245": { "Palette": "pal.9", "Width": 64 },
  "3dobj.246": { "Palette": "pal.9", "Width": 64 },
  "3dobj.247": { "Palette": "pal.7", "Width": 10 },
  "3dobj.248": { "Palette": "pal.7", "Width": 63, "Height": 101 },
  "3dobj.249": { "Palette": "pal.7", "Width": 31 },
  "3dobj.250": { "Palette": "pal.25", "Width": 39 },
  "3dobj.251": { "Palette": "pal.25", "Width": 63 },
  "3dobj.252": { "Palette": "pal.25", "Width": 60 },
  "3dobj.253": { "Palette": "pal.25", "Width": 119 },
  "3dobj.254": { "Palette": "pal.25", "Width": 89 },
  "3dobj.255": { "Palette": "pal.25", "Width": 66 },
  "3dobj.256": { "Palette": "pal.25", "Width": 42, "Height": 111 },
  "3dobj.257": { "Palette": "pal.25", "Width": 51, "Height": 129 },
  "3dobj.258": { "Palette": "pal.25", "Width": 51, "Height": 129 },
  "3dobj.259": { "Palette": "pal.25", "Width": 50, "Height": 128 },
  "3dobj.260": { "Palette": "pal.25", "Width": 50, "Height": 129 },
  "3dobj.261": { "Palette": "pal.8", "Width": 32 },
  "3dobj.262": { "Palette": "pal.8", "Width": 26 },
  "3dobj.263": { "Palette": "pal.8", "Width": 26 },
  "3dobj.264": { "Palette": "pal.25", "Width": 56, "Height": 129 },
  "3dobj.265": { "Palette": "pal.25", "Width": 56, "Height": 125 },
  "3dobj.266": { "Palette": "pal.25", "Width": 55, "Height": 129 },
  "3dobj.267": { "Palette": "pal.25", "Width": 56, "Height": 125 },
  "3dobj.268": { "Palette": "pal.25", "Width": 73, "Height": 130 },
  "3dobj.269": { "Palette": "pal.25", "Width": 60, "Height": 109 },
  "3dobj.270": { "Palette": "pal.25", "Width": 60, "Height": 109 },
  "3dobj.271": { "Palette": "pal.25", "Width": 45, "Height": 141 },
  "3dobj.272": { "Palette": "pal.25", "Width": 53, "Height": 141 },
  "3dobj.273": { "Palette": "pal.25", "Width": 47, "Height": 102 },
  "3dobj.274": { "Palette": "pal.25", "Width": 47, "Height": 103 },
  "3dobj.275": { "Palette": "pal.25", "Width": 61 },
  "3dobj.276": { "Palette": "pal.7", "Width": 64 },
  "3dobj.277": { "Palette": "pal.8", "Width": 26 },
  "3dobj.278": { "Palette": "pal.22", "Width": 64 },
  "3dobj.279": { "Palette": "pal.22", "Width": 64 },
  "3dobj.280": { "Palette": "pal.22", "Width": 64 },
  "3dobj.281": { "Palette": "pal.3", "Width": 145, "Height": 165 },
  "3dobj.282": { "Palette": "pal.3", "Width": 66 },
  "3dobj.283": { "Palette": "pal.3", "Width": 66 },
  "3dobj.284": { "Palette": "pal.9", "Width": 64 },
  "3dobj.285": { "Palette": "pal.9", "Width": 64 },
  "3dobj.286": { "Palette": "pal.3", "Width": 27, "Height": 74 },
  "3dobj.287": { "Palette": "pal.3", "Width": 27, "Height": 74 },
  "3dobj.288": { "Palette": "pal.15", "Width": 116 },
  "3dobj.289": { "Palette": "pal.3", "Width": 145, "Height": 165 },
  "3dobj.290": { "Palette": "pal.3", "Width": 81, "Height": 118 },
  "3dobj.291": { "Palette": "pal.3", "Width": 56, "Height": 56 },
  "3dobj.292": { "Palette": "pal.15", "Width": 85, "Height": 122 },
  "3dobj.293": { "Palette": "pal.3", "Width": 81, "Height": 119 },
  "3dobj.294": { "Palette": "pal.3", "Width": 155, "Height": 172 },
  "3dobj.295": { "Palette": "pal.15", "Width": 165, "Height": 147 },
  "3dobj.296": { "Palette": "pal.3", "Width": 24, "Height": 78 },
  "3dobj.297": { "Palette": "pal.3", "Width": 24, "Height": 70 },
  "3dobj.298": { "Palette": "pal.30", "Width": 51, "Height": 130 },
  "3dobj.299": { "Palette": "pal.30", "Width": 56, "Height": 129 }
}
